tripser/__init__.py
tripser/cli.py
tripser/tripser.py
pytripalserializer-0.0.2.dist-info/LICENSE
pytripalserializer-0.0.2.dist-info/METADATA
pytripalserializer-0.0.2.dist-info/WHEEL
pytripalserializer-0.0.2.dist-info/entry_points.txt
pytripalserializer-0.0.2.dist-info/RECORD
